wiki2crm/__init__.py
wiki2crm/__main__.py
wiki2crm/authors.py
wiki2crm/cli.py
wiki2crm/map_and_align.py
wiki2crm/merge.py
wiki2crm/relations.py
wiki2crm/resources.py
wiki2crm/works.py
wiki2crm/shapes/author-shapes.ttl
wiki2crm/shapes/relations-shapes.ttl
wiki2crm/shapes/work-shapes.ttl
wiki2crm-0.1.2.dist-info/METADATA
wiki2crm-0.1.2.dist-info/WHEEL
wiki2crm-0.1.2.dist-info/entry_points.txt
wiki2crm-0.1.2.dist-info/top_level.txt
wiki2crm-0.1.2.dist-info/RECORD
