Metadata-Version: 2.4
Name: wiki2crm
Version: 0.1.2
Summary: Tools to convert Wikidata to CIDOC CRM (eCRM/LRMoo/INTRO)
Author: Laura Untner
License: MIT License
Classifier: Programming Language :: Python :: 3
Classifier: License :: OSI Approved :: MIT License
Classifier: Operating System :: OS Independent
Requires-Python: >=3.9
Requires-Dist: rdflib
Requires-Dist: requests
Requires-Dist: tqdm
Requires-Dist: pyshacl
